refgenie/__init__.py
refgenie/__main__.py
refgenie/_version.py
refgenie/add_assets_igenome.py
refgenie/argparser.py
refgenie/asset_build_packages.py
refgenie/build_all_genome.py
refgenie/cli.py
refgenie/const.py
refgenie/exceptions.py
refgenie/helpers.py
refgenie/refgenie.py
refgenie/refget.py
refgenie/schemas/recipe_schema.yaml
refgenie-0.12.1.dist-info/LICENSE.txt
refgenie-0.12.1.dist-info/METADATA
refgenie-0.12.1.dist-info/WHEEL
refgenie-0.12.1.dist-info/entry_points.txt
refgenie-0.12.1.dist-info/top_level.txt
refgenie-0.12.1.dist-info/RECORD
