Metadata-Version: 2.1
Name: refgenie
Version: 0.12.1
Summary: Refgenie creates a standardized folder structure for reference genome files and indexes. You can download pre-built genomes or build your own for any fasta file
Home-page: http://refgenie.databio.org
Author: Nathan Sheffield, Vince Reuter, Michal Stolarczyk
License: BSD2
Keywords: bioinformatics,sequencing,ngs
Platform: UNKNOWN
Classifier: Development Status :: 4 - Beta
Classifier: License :: OSI Approved :: BSD License
Classifier: Programming Language :: Python :: 3.5
Classifier: Programming Language :: Python :: 3.6
Classifier: Programming Language :: Python :: 3.7
Classifier: Programming Language :: Python :: 3.8
Classifier: Programming Language :: Python :: 3.9
Classifier: Topic :: Scientific/Engineering :: Bio-Informatics
License-File: LICENSE.txt
